<?xml version="1.0" encoding="UTF-8"?>
<!DOCTYPE mtext [
<!ELEMENT mtext (property* , body+)>
<!ELEMENT property EMPTY>
<!ELEMENT body (#PCDATA)>
<!ATTLIST property key CDATA #REQUIRED>
<!ATTLIST property value CDATA #REQUIRED>
<!ATTLIST property from CDATA #REQUIRED>
<!ATTLIST property to CDATA #REQUIRED>
<!ATTLIST property control CDATA #REQUIRED>
]>
<mtext>
<property key="language" value="el" from="175" to="205" control="0"/>
<property key="language" value="ru" from="139" to="175" control="0"/>
<property key="language" value="sk" from="106" to="139" control="0"/>
<property key="language" value="de" from="64" to="106" control="0"/>
<property key="language" value="fr" from="27" to="64" control="0"/>
<property key="language" value="en" from="7" to="27" control="0"/>
<property key="language" value="am" from="409" to="432" control="0"/>
<property key="language" value="he" from="378" to="409" control="0"/>
<property key="language" value="fa" from="346" to="378" control="0"/>
<property key="language" value="ar" from="293" to="346" control="0"/>
<property key="language" value="ka" from="259" to="293" control="0"/>
<property key="language" value="tr" from="230" to="259" control="0"/>
<property key="language" value="lo" from="775" to="814" control="0"/>
<property key="language" value="th" from="734" to="775" control="0"/>
<property key="language" value="vi" from="698" to="734" control="0"/>
<property key="language" value="km" from="656" to="698" control="0"/>
<property key="language" value="bo" from="595" to="656" control="0"/>
<property key="language" value="ta" from="568" to="595" control="0"/>
<property key="language" value="ml" from="521" to="568" control="0"/>
<property key="language" value="bn" from="492" to="521" control="0"/>
<property key="language" value="hi" from="455" to="492" control="0"/>
<property key="language" value="ko" from="873" to="896" control="0"/>
<property key="language" value="zh" from="850" to="873" control="0"/>
<property key="language" value="ja" from="825" to="850" control="0"/>
<body>Europe
  English					Hello
  French (français)			Bonjour, Salut
  German (Deutsch)			Guten Tag, Grüß Gott
  Slovak (slovensky)			Dobrý deň
  Russian (русский)			Здравствуйте!
  Greek (ελληνικά)			Γειά σας

Middle Near East/Africa
  Turkish (Türkçe)			Merhaba
  Georgian (ქართული)		გამარჯობათ!
  Arabic (اَلْعَرَبِيَّةُ)‎				اَلسَّلَامُ عَلَيْكُم
  Persian (فارسی)‎			سلام عليکم
  Hebrew (עִבְרִית)‎			שָׁלוֹם
  Amharic (አማርኛ)			ሠላም

South/South-East Asia
  Hindi (हिंदी)				नमस्ते, नमस्कार ।
  Bengali (বাংলা)				নমস্কার
  Malayalam (മലയാളം)		നമസ്കാരം (ex: ന+്+ര=ന്ര)
  Tamil (தமிழ்)				வணக்கம்
  Tibetan (བོད་སྐད་)			བཀྲ་ཤིས་བདེ་ལེགས༎ (ex: བསྒྲུབས, ཧཱུཾ)
  Khmer (ខ្មៃរ)				ជំរាបសួរ (ex: ក្ក្រឿ៌)
  Vietnamese (Tiếng Việt)		Chào bạn
  Thai (ภาษาไทย)			สวัสดีครับ, สวัสดีค่ะ
  Lao (ພາສາລາວ)				ສະບາຍດີ, ຂໍໃຫ້ໂຊກດີ

East Asia
  Japanese (日本語)			こんにちは
  Chinese (汉语,普通话)		你好
  Korean (한글)				안녕하세요
</body></mtext>
